simple_test_packet/__init__.py
simple_test_packet/config.py
simple_test_packet/main.py
simple_test_packet/models.py
simple_test_packet-0.3.0.dist-info/entry_points.txt
simple_test_packet-0.3.0.dist-info/WHEEL
simple_test_packet-0.3.0.dist-info/METADATA
simple_test_packet-0.3.0.dist-info/RECORD
